kubeflow/__init__.py
kubeflow/utils/__init__.py
kubeflow/utils/docker.py
kubeflow/utils/kaggle.py
kubeflow_utils-0.0.1.dist-info/LICENSE
kubeflow_utils-0.0.1.dist-info/METADATA
kubeflow_utils-0.0.1.dist-info/WHEEL
kubeflow_utils-0.0.1.dist-info/top_level.txt
kubeflow_utils-0.0.1.dist-info/RECORD
